Workbook

Sheet APPENDIX
B6: Musk Business Ecosystem: Financial, Strategic & Risk Analysis
B8: Project objective
B9: Conduct an independent, evidence-based assessment of Elon Musk's business ecosystem, evaluating financial performance, growth strategies, capital requirements, corporate relationships, and material risks.
B11: Research scope
B12: Tesla
B14: SpaceX and Starlink
B16: xAI and X
B18: Neuralink
B20: The Boring Company
B23: Core deliverables
B25: Individual company financial and strategic assessments.
B27: Historical financial analysis and forward-looking scenarios where data permits.
... B37: A final executive report with findings, limitations, and recommendations.

Sheet TESLA inc. HFP  
B2: TESLA, INC. Historical fiancial performance
B3: Company Analysis | Fiscal Years 2023–2025
L6: Tesla's total revenue declined 2.9% in 2025, from $97.69 billion to $94.83 billion. Automotive revenue fell 9.8%, while energy generation and storage revenue increased 26.6%. Tesla attributed the automotive sales decline primarily to approximately 8% fewer cash deliveries and a lower average selling price per vehicle, driven by sales mix and customer incentives. Energy growth was primarily supported by increased Megapack and Powerwall deployments. Profitability weakened considerably. Operating income fell 38.5%, from $7.08 billion to $4.36 billion, and the operating margin declined from 7.2% to 4.6%. Tesla's research and development expenses increased from $4.54 billion to $6.41 billion, contributing to higher operating expenses. Meanwhile, operating cash flow declined only 1.2%, to $14.75 billion, and capital expenditures decreased 24.8%, to $8.53 billion. Overall, the results show a shift in Tesla's growth mix toward energy storage, alongside pressure on automotive revenue and overall operating profitability. The next stage should examine segment gross margins, operating expense growth, and the company's planned investments to determine whether these trends are sustainable.
B9: Note: USD millions $
D10: 2025 | E10: 2024 | F10: 2023
H11: Revenue growth (YoY) | I11: operating margin
B12: Total revenue | D12: 94827 | E12: 97990 | F12: 96773 | H12: =(D12-E12)/E12 -> -0.032278804 | I12: =D15/D12 -> 0.045925738
B13: Automotive revenue | D13: 69526 | E13: 77070 | F13: 82419 | H13: =(D13/E13)-1 -> -0.09788504
B14: energy generation and storage revenue | D14: 12771 | E14: 10086 | F14: 6035 | H14: =(D14/E14)-1 -> 0.26621059
B15: operating income | D15: 4355 | E15: 7076 | F15: 8891 | H15: =(D15/E15)-1 -> -0.38453929
B16: net income | D16: 3855 | E16: 7153 | F16: 14974 | H16: =(D16/E16)-1 -> -0.46106529
B17: operating cashflow | D17: 14747 | E17: 14923 | F17: 13256 | H17: =(D17/E17)-1 -> -0.011793875
B18: capital expenditures | D18: 8527 | E18: 11342 | F18: 8899 | H18: =(D18/E18)-1 -> -0.24819256
A23: - | N23: source:
L26: Revenue Mix Analysis: Key Findings Tesla's revenue mix changed significantly between 2023 and 2025. Automotive revenue declined from $82.42 billion in 2023 to $69.53 billion in 2025, reducing its share of total revenue from approximately 85% to 73%. This indicates that Tesla's overall revenue has become less concentrated in automotive sales, although automotive remains its largest source of revenue. In contrast, energy generation and storage revenue more than doubled, increasing from $6.04 billion in 2023 to $12.77 billion in 2025. Its share of total revenue rose from approximately 6% to 13%. Services and other revenue also increased, from $8.32 billion to $12.53 billion, growing from approximately 9% to 13% of total revenue. Despite growth in energy and services, these increases did not fully offset the decline in automotive revenue. Total revenue decreased from $96.77 billion in 2023 to $94.83 billion in 2025. This suggests Tesla's expanding energy business is becoming increasingly important, but the company remains exposed to changes in automotive demand, pricing, and competition. The next step is to compare year-over-year growth across these revenue categories to determine how quickly each business is changing and whether growth in energy and services can continue to offset automotive weakness.
B32: Revenue Mix Analysis (USD Millions)
D33: 2025 | E33: 2024 | F33: 2023
B34: automotive revenue | D34: 69559 | E34: 77070 | F34: 82419
B35: energy generation and storage | D35: 12771 | E35: 10086 | F35: 6035
B36: services and other | D36: 12530 | E36: 10534 | F36: 8319
B37: total revenue | D37: 94827 | E37: 97690 | F37: 96773
B38: automotive % of total | D38: =D34/D37 -> 0.73353581 | E38: =E34/E37 -> 0.78892415 | F38: =F34/F37 -> 0.8516735
B39: energy % of total | D39: =D35/D37 -> 0.13467683 | E39: =E35/E37 -> 0.10324496 | F39: =F35/F37 -> 0.062362436
B40: services % of total | D40: =D36/D37 -> 0.13213536 | E40: =E36/E37 -> 0.10783089 | F40: =F36/F37 -> 0.08596406
N46: source:
L48: Year-over-Year Revenue Growth: Key Findings Tesla's revenue trends show a growing difference between its automotive business and its other revenue categories. Automotive revenue declined by approximately 9.8% in 2025, following a 6.5% decline in 2024. This marks two consecutive years of declining automotive revenue and highlights the company's exposure to vehicle demand, pricing, and competition. In contrast, energy generation and storage revenue increased by 26.6% in 2025, following growth of approximately 67.1% in 2024. Although the growth rate slowed, the segment continued expanding rapidly. Services and other revenue also grew, increasing by 18.9% in 2025 after rising 26.6% in 2024. Despite growth in energy and services, total revenue declined by 2.9% in 2025 after increasing by approximately 0.9% in 2024. This indicates that growth outside automotive has not yet fully offset the decline in automotive revenue. From a financial risk perspective, Tesla's expanding energy business provides greater revenue diversification, but continued weakness in automotive remains a significant concern. These trends warrant further investigation into segment profitability, operating expenses, and cash generation to determine whether growth in newer business areas can support Tesla's overall financial performance.
B55: Year over year Revenue growth
B56: Revenue category | C56: 2025 vs. 2024 | E56: 2024 vs 2023
B57: automotive revenue | C57: =(D34/E34)-1 -> -0.097456857 | E57: =(E34/F34)-1 -> -0.064900084
B58: energy generation and storage | C58: =(D35/E35)-1 -> 0.26621059 | E58: =(E35/F35)-1 -> 0.67125104
B59: services and other | C59: =(D36/E36)-1 -> 0.18948168 | E59: =(E36/F36)-1 -> 0.26625796
B60: total revenue | C60: =(D37/E37)-1 -> -0.029306992 | E60: =(E37/F37)-1 -> 0.0094757835
N68: source:
L73: Profitability Analysis: Tesla's profitability weakened significantly between 2023 and 2025. Gross profit remained relatively stable, declining from $17.66 billion in 2023 to $17.09 billion in 2025. However, gross margin stayed around 18% across all three years, suggesting that Tesla maintained a relatively consistent relationship between revenue and the direct costs of producing its products. Operating income declined from $8.89 billion in 2023 to $4.36 billion in 2025. As a result, operating margin fell from approximately 9% to 5%, indicating that Tesla generated less operating profit from each dollar of revenue. Net income also dropped sharply, from $14.97 billion in 2023 to $3.86 billion in 2025, reducing net profit margin from approximately 15% to 4%. The decline in operating and net income, despite relatively stable gross profit, suggests that costs below the gross profit line and changes in non-operating income and expenses played an important role in Tesla's reduced profitability. This raises concerns about the company's ability to maintain earnings as automotive revenue declines. The next step is to examine Tesla's operating expenses and cash flow to better understand what is driving the decline in profitability.
B80: Profitability analysis | D80: 2025 | E80: 2024 | F80: 2023
B82: gross profit | D82: 17094 | E82: 17450 | F82: 17660
B83: Gross margin | D83: =D82/D12 -> 0.18026511 | E83: =E82/E12 -> 0.1780794 | F83: =F82/F12 -> 0.18248892
B84: operating income | D84: 4355 | E84: 7076 | F84: 8891
B85: operating margin | D85: =D84/D12 -> 0.045925738 | E85: =E84/E12 -> 0.07221145 | F85: =F84/F12 -> 0.0918748
B86: net income | D86: =3855 -> 3855 | E86: 7153 | F86: 14974
B87: netprofit margin | D87: =D86/D12 -> 0.040652979 | E87: =E86/E12 -> 0.072997245 | F87: =F86/F12 -> 0.15473324
L94: Cash Flow and Capital Investment Analysis: Tesla continued generating strong operating cash flow between 2023 and 2025, although it declined slightly from $14.92 billion in 2024 to $14.75 billion in 2025. This shows that the company continued generating substantial cash from its operations despite weaker profitability. Capital expenditures decreased from $11.34 billion in 2024 to $8.53 billion in 2025. As a result, free cash flow increased from $3.58 billion to $6.22 billion, meaning Tesla retained more cash after capital investments. However, this improvement was driven largely by lower capital spending rather than an increase in operating cash flow. Free cash flow was also higher in 2025 than in 2023, when it stood at $4.36 billion. This indicates that Tesla's cash generation after capital expenditures improved over the three-year period, even as net income declined substantially. From a financial risk perspective, Tesla's positive free cash flow provides flexibility to fund future projects and manage financial obligations. However, lower capital expenditures do not necessarily indicate improved operational performance, especially as Tesla continues investing in manufacturing, AI infrastructure, and other growth initiatives. The key question is whether the company can sustain strong cash generation while increasing investment in future growth.
B100: CF & Capital investment analysis | D100: 2025 | E100: 2024 | F100: 2023
B102: operating CF | D102: =D17 -> 14747 | E102: =E17 -> 14923 | F102: =F17 -> 13256
B103: capital expenditures | D103: =D18 -> 8527 | E103: =E18 -> 11342 | F103: =F18 -> 8899
B104: free cash flow | D104: =D102-D103 -> 6220 | E104: =E102-E103 -> 3581 | F104: =F102-F103 -> 4357
B105: operating cash flow margin | D105: =D102/D12 -> 0.15551478 | E105: =E102/E12 -> 0.15229105 | F105: =F102/F12 -> 0.13698036
B106: free cash flow margin | D106: =D104/D12 -> 0.065593133 | E106: =E104/E12 -> 0.036544545 | F106: =F104/F12 -> 0.045022889
B107: capital expenditures / revenue | D107: =D103/D12 -> 0.089921647 | E107: =E103/E12 -> 0.1157465 | F107: =F103/F12 -> 0.091957467
L115: Balance Sheet and Financial Strength: Tesla's short-term liquidity improved between 2024 and 2025. Its current ratio increased from 2.02x to 2.16x, meaning the company had approximately $2.16 in current assets for every $1 of current liabilities in 2025. Cash and short-term investments also increased from approximately $36.56 billion to $44.06 billion, giving Tesla a larger pool of liquid resources. Tesla's debt-to-equity ratio decreased from approximately 11% to 10%, while total liabilities remained around 40% of total assets. These figures suggest that Tesla's overall balance sheet structure remained relatively stable, with reported debt and finance leases representing a relatively small share of stockholders' equity. From a financial risk perspective, Tesla's growing liquidity and relatively low debt-to-equity ratio provide a degree of financial flexibility. However, liquidity ratios alone do not establish that all assets can be converted into cash immediately, and total liabilities include more than debt. Further analysis should consider the composition of liabilities, future investment needs, and the sustainability of operating cash flow. Overall, Tesla's balance sheet appears stronger on short-term liquidity in 2025 than in 2024. The next step is to combine these findings with revenue, profitability, and cash flow trends to form an overall assessment of Tesla's historical financial performance.
B118: BS and Financial strenght | D118: 2025 | E118: 2024
B120: cash | D120: 16513 | E120: 16139
B121: short term investment | D121: 27546 | E121: 20424
B122: total current assets | D122: 68642 | E122: 58360
B123: total current liabilities | D123: 31714 | E123: 28821
B124: total assets | D124: 137806 | E124: 122070
B125: total liabilitlies | D125: 54941 | E125: 48390
B126: total stock holder equity | D126: 82137 | E126: 72913
B127: total debt and finance lease | D127: 8376 | E127: 8213
B129: current ratio | D129: =D122/D123 -> 2.1644069 | E129: =E122/E123 -> 2.0249124
B130: debt to equity ratio | D130: =D127/D126 -> 0.10197597 | E130: =E127/E126 -> 0.11264109
B131: liabilities to asset ratios | D131: =D125/D124 -> 0.39868366 | E131: =E125/E124 -> 0.39641189
B137: Tesla Historical Performance: Overall Conclusion Tesla's financial performance weakened in several important areas between 2023 and 2025. Total revenue declined from $96.77 billion in 2023 to $94.83 billion in 2025, primarily reflecting declining automotive revenue. Automotive revenue fell for two consecutive years, while energy generation and storage and services revenue continued to grow. This indicates that Tesla's revenue mix is becoming more diversified, although the automotive business remains its largest source of revenue. Profitability also deteriorated. Operating income declined from $8.89 billion in 2023 to $4.36 billion in 2025, while net income fell from $14.97 billion to $3.86 billion. Despite relatively stable gross margins, Tesla generated substantially less operating and net income, highlighting the need to investigate operating expenses and non-operating items further. Cash flow provides a more positive picture. Tesla generated $14.75 billion in operating cash flow and $6.22 billion in free cash flow in 2025. Free cash flow improved compared with both 2024 and 2023, largely because capital expenditures decreased. However, future investment requirements could affect whether this improvement is sustainable. Tesla's balance sheet also showed positive signs. Its current ratio increased to 2.16x in 2025, and its debt-to-equity ratio declined to approximately 10%. These figures suggest the company maintained a solid short-term liquidity position and relatively low debt compared with equity, although its full financial risk profile also depends on other liabilities and future cash needs. Overall, Tesla's main financial strengths are its ability to generate operating cash flow, its substantial liquid resources, and the growth of its energy business. Its main concerns are declining automotive revenue, weakening profitability, and uncertainty over whether lower capital spending can continue supporting free cash flow. These findings establish a historical baseline for the next phase of analysis, where we can investigate the drivers of performance and develop assumptions for future financial projections and valuation.

Sheet tesla financial modeling 
J3: EBITDA Proxy Analysis: Tesla's EBITDA proxy declined from approximately $13.56 billion in 2023 to $10.50 billion in 2025. Its EBITDA proxy margin also decreased from approximately 14.0% to 11.1%, indicating that the company generated less operating earnings, before depreciation and amortization adjustments, for each dollar of revenue. This decline is consistent with the weaker operating performance identified in (tesla HFP sheet). Tesla's operating income fell from $8.89 billion in 2023 to $4.36 billion in 2025, while total revenue also declined. This suggests that the reduction in earnings was not caused by lower revenue alone; Tesla's ability to convert revenue into operating profit also weakened. From a financial analysis perspective, the declining EBITDA proxy margin raises questions about automotive pricing, production costs, operating expenses, and Tesla's ability to maintain profitability as its business mix changes. Growth in energy generation and storage may help offset weakness in automotive, but further analysis is needed to determine how these businesses contribute to earnings. Overall, the EBITDA proxy provides another indication that Tesla's operating performance weakened between 2023 and 2025. The next step is to examine operating expenses and other factors that contributed to this decline before using historical performance to build financial forecasts.
B9: EBITDA proxy
D10: 2025 | E10: 2024 | F10: 2023
B11: operating income | D11: 4355 | E11: ='TESLA inc. HFP '!E84 -> 7076 | F11: ='TESLA inc. HFP '!F84 -> 8891
B12: depreciation, amorization and impairment | D12: 6148 | E12: 6148 | F12: 6148
B13: EBITDA PROXY | D13: =D12+D11 -> 10503 | E13: =E12+E11 -> 13224 | F13: =F12+F11 -> 15039
B14: EBOTDA PROXY Margin | D14: =D13/'TESLA inc. HFP '!D12 -> 0.11075959 | E14: =E13/'TESLA inc. HFP '!E12 -> 0.13495255 | F14: =F13/'TESLA inc. HFP '!F12 -> 0.15540492
J22: Operating Expense Analysis: Key Findings Tesla's total operating expenses increased from $8.77 billion in 2023 to $12.74 billion in 2025. Operating expenses also rose from 9.1% of revenue in 2023 to 13.4% in 2025, meaning a larger share of Tesla's revenue was used to cover research, administration, and restructuring costs. Research and development was the largest driver of this increase. R&D expenses rose from $3.97 billion in 2023 to $6.41 billion in 2025, increasing by approximately 61%. Tesla reported that the 2025 increase was primarily related to AI and other programs, along with higher stock-based compensation. This spending may support future growth, but it also puts pressure on current profitability. Selling, general and administrative expenses increased from $4.80 billion to $5.83 billion over the same period. Tesla also recorded $684 million in restructuring expenses in 2024 and $494 million in 2025. These additional costs contributed to the overall operating expense burden. From a financial risk perspective, rising operating expenses combined with declining revenue create pressure on operating margins. Tesla's investment in AI and other technologies could generate future returns, but the financial benefit will depend on whether these investments produce enough additional revenue and profit to justify their cost. Overall, operating expenses have grown faster than revenue, helping explain why Tesla's operating income and margins weakened. The next step is to connect these findings to a financial forecast and evaluate how changes in revenue growth and expenses could affect future profitability.
B25: Operating expense analysis
D26: 2025 | E26: 2024 | F26: 2023
B27: R&D | D27: 6411 | E27: 4540 | F27: 3969
B28: SG&A | D28: 5834 | E28: 5150 | F28: 4800
B29: restructuring and other | D29: 494 | E29: 684 | F29: 0
B30: total operating expenses | D30: =SUM(D27:D29) -> 12739 | E30: =SUM(E27:E29) -> 10374 | F30: =SUM(F27:F29) -> 8769
B31: R&D / revenue | D31: =D27/'TESLA inc. HFP '!D12 -> 0.067607327 | E31: =E27/'TESLA inc. HFP '!E12 -> 0.046331258 | F31: =F27/'TESLA inc. HFP '!F12 -> 0.041013506
B32: SG&A / revenue | D32: =D28/'TESLA inc. HFP '!D12 -> 0.061522562 | E32: =E28/'TESLA inc. HFP '!E12 -> 0.052556383 | F32: =F28/'TESLA inc. HFP '!F12 -> 0.049600612
B33: total operating expenses / revenue | D33: =D30/'TESLA inc. HFP '!D12 -> 0.13433938 | E33: =E30/'TESLA inc. HFP '!E12 -> 0.10586795 | F33: =F30/'TESLA inc. HFP '!F12 -> 0.090614118
B42: Income statement ($millions)
D43: 2025 | E43: 2024 | F43: 2023
B44: total revenue | D44: 94827 | E44: 97690 | F44: 96773
B45: cost of revenue | D45: 77733 | E45: 80240 | F45: 79113
B46: gross profit | D46: 17094 | E46: 17450 | F46: 17660 | J46: Tesla's operating cash flow increased from $13.26 billion in 2023 to $14.75 billion in 2025, showing that the company maintained strong cash generation despite declining revenue and profitability. However, operating cash flow decreased slightly from 2024 to 2025, suggesting that cash generation has remained relatively stable rather than experiencing significant growth. Capital expenditures decreased from $11.34 billion in 2024 to $8.53 billion in 2025, a reduction of approximately 25%. This decline helped Tesla preserve more cash, although lower capital spending does not necessarily indicate improved operating performance. Future investment requirements for AI, manufacturing, and energy infrastructure could increase capital expenditures again. Free cash flow increased from $3.58 billion in 2024 to $6.22 billion in 2025, representing approximately 74% growth. This improvement was primarily driven by reduced capital expenditures rather than stronger operating cash flow. From a financial risk perspective, Tesla's positive free cash flow provides financial flexibility, but long-term sustainability will depend on improving profitability while funding future investments.
B47: R&D | D47: 6411 | E47: 4540 | F47: 3969
B48: SG&A | D48: 5834 | E48: 5150 | F48: 4800
B49: restructuring and other | D49: 494 | E49: 684 | F49: 0
B50: total operating expenses | D50: =SUM(D47:D49) -> 12739 | E50: =SUM(E47:E49) -> 10374 | F50: =SUM(F47:F49) -> 8769
B51: operating income | D51: =D46-D50 -> 4355 | E51: =E46-E50 -> 7076 | F51: =F46-F50 -> 8891
B52: interest income | D52: =1680 -> 1680 | E52: 1569 | F52: 1066
B53: interest expense | D53: =-338 -> -338 | E53: -350 | F53: -156
B54: other expense income, net | D54: -419 | E54: 695 | F54: 172
B55: income before taxes | D55: =SUM(D51:D54) -> 5278 | E55: =SUM(E51:E54) -> 8990 | F55: =SUM(F51:F54) -> 9973
B56: provision for income taxes | D56: 1423 | E56: 1837 | F56: -5001
B57: net income | D57: =D55-D56 -> 3855 | E57: =E55-E56 -> 7153 | F57: =F55-F56 -> 14974
B59: Balance sheet ($millions)
D60: 2025 | E60: 2024
B61: cash | D61: 16513 | E61: 16139
B62: short term investments | D62: 27546 | E62: 20424
B63: accounts receivvable | D63: 4576 | E63: 4418
B64: prepaid expenses and other CA | D64: 7615 | E64: 5362
B65: inventory | D65: 12392 | E65: 12017
B66: total current assets | D66: =SUM(D61:D65) -> 68642 | E66: =SUM(E61:E65) -> 58360
B67: property, plant and equipment | D67: 40643 | E67: 35836
B68: total non current assets | D68: 69164 | E68: =63710 -> 63710
B69: total assets | D69: =D66+D68 -> 137806 | E69: =E66+E68 -> 122070
B70: total current liabilities | D70: 31714 | E70: 28821
B71: total non current liabilities | D71: 23227 | E71: 19569
B72: total debts and finance leases | D72: 8376 | E72: 8213
B73: total liabilities | D73: =SUM(D70,D71) -> 54941 | E73: =SUM(E70,E71) -> 48390
B74: reedemable non controlling interest | D74: 58 | E74: 63
B75: non controlling interest in subsidiaries | D75: 670 | E75: 704
B76: total stockholder equity | D76: =D69-D73-D74-D75 -> 82137 | E76: =E69-E73-E74-E75 -> 72913
B79: cash flows ($millions)
D80: 2025 | E80: 2024 | F80: 2023
B81: operating cash flow | D81: 14747 | E81: 14923 | F81: 13256
B82: capital expenditures | D82: 8527 | E82: 11342 | F82: 8899
B83: free cash flows | D83: =D81-D82 -> 6220 | E83: =E81-E82 -> 3581 | F83: =F81-F82 -> 4357

Sheet TSLA forecastin & evaluation 
B3: revenue forcast
D4: 2025 actual | E4: 2026 forecast | F4: 2027 forecast | G4: 2028 forecast | H4: 2029 forecast | I4: 2030 forecast | L4: Tesla's total revenue is projected to increase from $94.83 billion in 2025 to approximately $141.27 billion by 2030, representing roughly 49% cumulative growth. This forecast assumes a gradual recovery in automotive revenue alongside continued expansion in energy generation and storage. Energy is expected to be one of Tesla's strongest growth drivers, with projected revenue increasing from $12.77 billion in 2025 to approximately $30.45 billion by 2030. Meanwhile, automotive revenue is projected to reach $87.75 billion, reflecting a more conservative recovery following recent declines. From a financial risk perspective, these projections depend on Tesla maintaining demand, managing competition, and successfully expanding its energy business. Actual performance could differ significantly from these assumptions, making scenario and sensitivity analysis important in later stages of the valuation.
B5: automotive | D5: =69526 -> 69526 | E5: =D5*(1+E13+$C$202) -> 69526 | F5: =E5*(1+F13+$C$202) -> 72307.04 | G5: =F5*(1+G13+$C$202) -> 76645.462 | H5: =G5*(1+H13+$C$202) -> 82010.645 | I5: =H5*(1+I13+$C$202) -> 87751.39
B6: energy generation & storage | D6: 12771 | E6: =D6*(1+E14+$C$202) -> 15325.2 | F6: =E6*(1+F14+$C$202) -> 18696.744 | G6: =F6*(1+G14+$C$202) -> 22436.093 | H6: =G6*(1+H14+$C$202) -> 26474.59 | I6: =H6*(1+I14+$C$202) -> 30445.778
B7: services and other | D7: 12530 | E7: =D7*(1+E15+$C$202) -> 14409.5 | F7: =E7*(1+F15+$C$202) -> 16570.925 | G7: =F7*(1+G15+$C$202) -> 18725.145 | H7: =G7*(1+H15+$C$202) -> 20972.163 | I7: =H7*(1+I15+$C$202) -> 23069.379
B8: total revenue | D8: =SUM(D5:D7) -> 94827 | E8: =SUM(E5:E7) -> 99260.7 | F8: =SUM(F5:F7) -> 107574.71 | G8: =SUM(G5:G7) -> 117806.7 | H8: =SUM(H5:H7) -> 129457.4 | I8: =SUM(I5:I7) -> 141266.55
B9: revenue growth % | E9: =(E8/D8)-1 -> 0.046755671 | F9: =(F8/E8)-1 -> 0.083759323 | G9: =(G8/F8)-1 -> 0.095115214 | H9: =(H8/G8)-1 -> 0.098896722 | I9: =(I8/H8)-1 -> 0.091220356
B11: revenue growth assumptions
D12: 2025 actual | E12: 2026 forecast | F12: 2027 forecast | G12: 2028 forecast | H12: 2029 forecast | I12: 2030 forecast
B13: automotive growth % | E13: 0 | F13: 0.04 | G13: 0.06 | H13: 0.07 | I13: 0.07
B14: energy growth | E14: 0.2 | F14: 0.22 | G14: 0.2 | H14: 0.18 | I14: 0.15
B15: services growth | E15: 0.15 | F15: 0.15 | G15: 0.13 | H15: 0.12 | I15: 0.1
L21: Profitability Forecast Analysis (2026–2030) Tesla's gross margin is projected to increase from 18.03% in 2025 to 23% by 2030. This forecast assumes that Tesla gradually improves manufacturing efficiency, benefits from economies of scale, and generates a larger share of revenue from its growing energy and services businesses. We assumed cost of revenue would decline from 81% of revenue in 2026 to 77% in 2030. These improvements are estimates rather than guaranteed outcomes, particularly given competition and potential pricing pressure in the automotive market. Research and development expenses are projected to remain relatively high, ranging from 7% of revenue in 2026 to 6.2% by 2030. This assumption reflects Tesla's continued investment in AI, autonomous driving, robotics, and energy technologies. Meanwhile, SG&A expenses are expected to decrease from 6% to 5.2% of revenue as the company grows and spreads administrative costs across a larger revenue base. Restructuring expenses are assumed to decline from $400 million in 2026 to $100 million in 2030, reflecting an expectation of fewer extraordinary restructuring costs. Under these assumptions, Tesla's operating income is projected to increase from $4.36 billion in 2025 to approximately $16.29 billion in 2030, with operating margins improving from 4.59% to 11.52%. This recovery depends heavily on revenue growth, cost control, and successful execution of Tesla's expansion strategy. From a financial risk perspective, weaker demand, higher production costs, or increased R&D spending could significantly reduce projected profitability. These assumptions will be tested later through scenario and sensitivity analysis.
B26: Profatibality forecast($millions)
D27: 2025 actual | E27: 2026 forecast | F27: 2027 forecast | G27: 2028 forecast | H27: 2029 forecast | I27: 2030 forecast
B28: total revenue | D28: 94827 | E28: =E8 -> 99260.7 | F28: =F8 -> 107574.71 | G28: =G8 -> 117806.7 | H28: =H8 -> 129457.4 | I28: =I8 -> 141266.55
B29: cost of revenue | D29: 77733 | E29: =E28*E41 -> 80401.167 | F29: =F28*F41 -> 86059.767 | G29: =G28*G41 -> 93067.293 | H29: =H28*H41 -> 100976.77 | I29: =I28*I41 -> 108775.24
B30: gross profit | D30: 17094 | E30: =E28-E29 -> 18859.533 | F30: =F28-F29 -> 21514.942 | G30: =G28-G29 -> 24739.407 | H30: =H28-H29 -> 28480.627 | I30: =I28-I29 -> 32491.306
B31: gross margin % | D31: =D30/D28 -> 0.18026511 | E31: =E30/E28 -> 0.19 | F31: =F30/F28 -> 0.2 | G31: =G30/G28 -> 0.21 | H31: =H30/H28 -> 0.22 | I31: =I30/I28 -> 0.23
B32: R&D expenses | D32: 6411 | E32: =E28*F42 -> 6948.249 | F32: =F28*G42 -> 7315.0802 | G32: =G28*H42 -> 7657.4355 | H32: =H28*I42 -> 8026.3586 | I32: =I28*I42 -> 8758.5259
B33: SG&A expenses | D33: 5834 | E33: =E28*E43 -> 5955.642 | F33: =F28*F43 -> 6239.3331 | G33: =G28*G43 -> 6597.1752 | H33: =H28*H43 -> 6990.6994 | I33: =I28*I43 -> 7345.8604
B34: restructuring and other | D34: 494 | E34: =E44 -> 400 | F34: =F44 -> 300 | G34: =G44 -> 200 | H34: =H44 -> 150 | I34: =I44 -> 100
B35: total operating expenses | D35: 12739 | E35: =SUM(E32:E34) -> 13303.891 | F35: =SUM(F32:F34) -> 13854.413 | G35: =SUM(G32:G34) -> 14454.611 | H35: =SUM(H32:H34) -> 15167.058 | I35: =SUM(I32:I34) -> 16204.386
B36: operating income | D36: 4355 | E36: =E30-E35+E28*$C$202 -> 5555.642 | F36: =F30-F35+F28*$C$202 -> 7660.5285 | G36: =G30-G35+G28*$C$202 -> 10284.796 | H36: =H30-H35+H28*$C$202 -> 13313.569 | I36: =I30-I35+I28*$C$202 -> 16286.919
B37: operating margin % | D37: =D36/D28 -> 0.045925738 | E37: =E36/E28 -> 0.055970208 | F37: =F36/F28 -> 0.07121124 | G37: =G36/G28 -> 0.087302304 | H37: =H36/H28 -> 0.10284132 | I37: =I36/I28 -> 0.11529212
B39: Profitability growth assumptions
D40: 2025 actual | E40: 2026 forecast | F40: 2027 forecast | G40: 2028 forecast | H40: 2029 forecast | I40: 2030 forecast
B41: cost of revenue % | E41: 0.81 | F41: 0.8 | G41: 0.79 | H41: 0.78 | I41: 0.77
B42: R&D % | E42: 0.07 | F42: 0.07 | G42: 0.068 | H42: 0.065 | I42: 0.062
B43: SG&A % | E43: 0.06 | F43: 0.058 | G43: 0.056 | H43: 0.054 | I43: 0.052
B44: restructuring (millions) | E44: 400 | F44: 300 | G44: 200 | H44: 150 | I44: 100
B50: net income forecast table
D51: 2025 actual | E51: 2026 forecast | F51: 2027 forecast | G51: 2028 forecast | H51: 2029 forecast | I51: 2030 forecast | L51: Tesla's net income is projected to increase from $3.86 billion in 2025 to approximately $12.93 billion by 2030, representing significant earnings growth over the forecast period. Net profit margin is expected to improve from 4.07% to 9.15%, driven primarily by higher revenue and improved operating efficiency. The forecast assumes gradually declining interest income, slightly increasing financing expenses, and a normalized effective tax rate of 25%. Other nonoperating income and expenses are assumed to be zero due to their unpredictable nature. Although the projections suggest a strong recovery in profitability, these results depend heavily on Tesla achieving its revenue growth targets and reducing operating costs as a percentage of revenue. Slower vehicle sales, increased competition, or higher operating expenses could materially reduce projected earnings.
B52: operating income | D52: =4355 -> 4355 | E52: =E36 -> 5555.642 | F52: =F36 -> 7660.5285 | G52: =G36 -> 10284.796 | H52: =H36 -> 13313.569 | I52: =I36 -> 16286.919
B53: interest income | D53: 1680 | E53: =E63 -> 1600 | F53: =F63 -> 1550 | G53: =G63 -> 1500 | H53: =H63 -> 1450 | I53: =I63 -> 1400
B54: interest expense | D54: -338 | E54: =E64 -> -350 | F54: =F64 -> -375 | G54: =G64 -> -400 | H54: =H64 -> -435 | I54: =I64 -> -450
B55: other income/expense | D55: -419 | E55: =E65 -> 0 | F55: =F65 -> 0 | G55: =G65 -> 0 | H55: =H65 -> 0 | I55: =I65 -> 0
B56: income before taxes | D56: 5278 | E56: =SUM(E52:E55) -> 6805.642 | F56: =SUM(F52:F55) -> 8835.5285 | G56: =SUM(G52:G55) -> 11384.796 | H56: =SUM(H52:H55) -> 14328.569 | I56: =SUM(I52:I55) -> 17236.919
B57: income tax expense | D57: 1423 | E57: =E56*E66 -> 1701.4105 | F57: =F56*F66 -> 2208.8821 | G57: =G56*G66 -> 2846.1991 | H57: =H56*H66 -> 3582.1423 | I57: =I56*I66 -> 4309.2299
B58: net income | D58: =D56-D57 -> 3855 | E58: =E56-E57 -> 5104.2315 | F58: =F56-F57 -> 6626.6463 | G58: =G56-G57 -> 8538.5973 | H58: =H56-H57 -> 10746.427 | I58: =I56-I57 -> 12927.69
B59: net profit margin % | D59: =D58/D28 -> 0.040652979 | E59: =E58/E8 -> 0.051422481 | F59: =F58/F8 -> 0.061600412 | G59: =G58/G8 -> 0.072479725 | H59: =H58/H8 -> 0.083011301 | I59: =I58/I8 -> 0.091512746
B61: net income growth assumptions
D62: 2025 actual | E62: 2026 forecast | F62: 2027 forecast | G62: 2028 forecast | H62: 2029 forecast | I62: 2030 forecast
B63: interest income | E63: 1600 | F63: 1550 | G63: 1500 | H63: 1450 | I63: 1400
B64: interest expense | E64: -350 | F64: -375 | G64: -400 | H64: -435 | I64: -450
B65: other income/ expense | E65: 0 | F65: 0 | G65: 0 | H65: 0 | I65: 0
B66: effective tax rate % | E66: 0.25 | F66: 0.25 | G66: 0.25 | H66: 0.25 | I66: 0.25
B72: cash flow forecast ($millions)
D73: 2025 actual | E73: 2026 forecast | F73: 2027 forecast | G73: 2028 forecast | H73: 2029 forecast | I73: 2030 forecast
B74: net income | D74: 3855 | E74: =E58 -> 5104.2315 | F74: =F58 -> 6626.6463 | G74: =G58 -> 8538.5973 | H74: =H58 -> 10746.427 | I74: =I58 -> 12927.69
B75: depreciation & amortization | D75: 6148 | E75: =E87*E28 -> 6451.9455 | F75: =F87*F28 -> 6777.2067 | G75: =G87*G28 -> 7068.402 | H75: =H87*H28 -> 7508.529 | I75: =I87*I28 -> 7769.6601 | L75: Tesla's operating cash flow is projected to increase from $14.75 billion in 2025 to approximately $22.82 billion by 2030, supported by stronger net income and continued business expansion. However, free cash flow is expected to decline from $6.22 billion in 2025 to approximately $2.54 billion in 2027, primarily due to elevated capital expenditures. The forecast assumes Tesla continues investing heavily in manufacturing capacity, energy infrastructure, and AI-related projects, temporarily reducing the cash available after investments. From 2028 onward, free cash flow is projected to recover, reaching approximately $8.69 billion by 2030 as earnings increase and capital expenditures decline relative to revenue. Despite this recovery, the projected 2030 free cash flow margin of 6.15% remains below the 2025 level of 6.56%. This suggests that Tesla's growth strategy could continue requiring substantial reinvestment, even as profitability improves. These projections are based on independent assumptions and remain sensitive to future capital spending, operating performance, and working capital requirements.
B76: stock based compensation | D76: 2825 | E76: =E88*E28 -> 2977.821 | F76: =F88*F28 -> 3119.6666 | G76: =G88*G28 -> 3298.5876 | H76: =H88*H28 -> 3495.3497 | I76: =I88*I28 -> 3531.6637
B77: change in working capital | D77: 642 | E77: =E89*E28 -> -992.607 | F77: =F89*F28 -> -1075.7471 | G77: =G89*G28 -> -1413.6804 | H77: =H89*H28 -> -1553.4888 | I77: =I89*I28 -> -2118.9982
B78: other operating adjustments | D78: 1277 | E78: =E90*E28 -> 992.607 | F78: =F90*F28 -> 1075.7471 | G78: =G90*G28 -> 942.4536 | H78: =H90*H28 -> 1035.6592 | I78: =I90*I28 -> 706.33273
B79: operating CF | D79: =SUM(D74:D78) -> 14747 | E79: =SUM(E74:E78) -> 14533.998 | F79: =SUM(F74:F78) -> 16523.52 | G79: =SUM(G74:G78) -> 18434.36 | H79: =SUM(H74:H78) -> 21232.476 | I79: =SUM(I74:I78) -> 22816.348
B80: capital expenditures | D80: 8527 | E80: =E28*E91*(1+$C$203) -> 11911.284 | F80: =F28*F91*(1+$C$203) -> 13984.712 | G80: =G28*G91*(1+$C$203) -> 14136.804 | H80: =H28*H91*(1+$C$203) -> 14240.314 | I80: =I28*I91*(1+$C$203) -> 14126.655
B81: FCF | D81: 6220 | E81: =E79-E80 -> 2622.714 | F81: =F79-F80 -> 2538.8074 | G81: =G79-G80 -> 4297.556 | H81: =H79-H80 -> 6992.1625 | I81: =I79-I80 -> 8689.6932
B82: FCF % | D82: =D81/D28 -> 0.065593133 | E82: =E81/E28 -> 0.026422481 | F82: =F81/F28 -> 0.023600412 | G82: =G81/G28 -> 0.036479725 | H82: =H81/H28 -> 0.054011301 | I82: =I81/I28 -> 0.061512746
B85: cash flows assumptions
D86: 2025 actual | E86: 2026 forecast | F86: 2027 forecast | G86: 2028 forecast | H86: 2029 forecast | I86: 2030 forecast
B87: D&A | E87: 0.065 | F87: 0.063 | G87: 0.06 | H87: 0.058 | I87: 0.055
B88: stock based comp | E88: 0.03 | F88: 0.029 | G88: 0.028 | H88: 0.027 | I88: 0.025
B89: change in working capital | E89: -0.01 | F89: -0.01 | G89: -0.012 | H89: -0.012 | I89: -0.015
B90: other op. adjustsment | E90: 0.01 | F90: 0.01 | G90: 0.008 | H90: 0.008 | I90: 0.005
B91: capital expenditures | E91: 0.12 | F91: 0.13 | G91: 0.12 | H91: 0.11 | I91: 0.1
B95: Unlevered FCF forecast ($millions)
D96: 2025 actual | E96: 2026 forecast | F96: 2027 forecast | G96: 2028 forecast | H96: 2029 forecast | I96: 2030 forecast
B97: Operating income (ebit) | E97: =E36 -> 5555.642 | F97: =F36 -> 7660.5285 | G97: =G36 -> 10284.796 | H97: =H36 -> 13313.569 | I97: =I36 -> 16286.919
B98: tax rate % | E98: =E66 -> 0.25 | F98: =F66 -> 0.25 | G98: =G66 -> 0.25 | H98: =H66 -> 0.25 | I98: =I66 -> 0.25
B99: taxes on EBIT | E99: =E97*E98 -> 1388.9105 | F99: =F97*F98 -> 1915.1321 | G99: =G97*G98 -> 2571.1991 | H99: =H97*H98 -> 3328.3923 | I99: =I97*I98 -> 4071.7299
B100: NOPAT | E100: =E97-E99 -> 4166.7315 | F100: =F97-F99 -> 5745.3963 | G100: =G97-G99 -> 7713.5973 | H100: =H97-H99 -> 9985.177 | I100: =I97-I99 -> 12215.19
B101: D&A | E101: =E75 -> 6451.9455 | F101: =F75 -> 6777.2067 | G101: =G75 -> 7068.402 | H101: =H75 -> 7508.529 | I101: =I75 -> 7769.6601
B102: stock based comp | E102: =E76 -> 2977.821 | F102: =F76 -> 3119.6666 | G102: =G76 -> 3298.5876 | H102: =H76 -> 3495.3497 | I102: =I76 -> 3531.6637
B103: change in working capital | E103: =E77 -> -992.607 | F103: =F77 -> -1075.7471 | G103: =G77 -> -1413.6804 | H103: =H77 -> -1553.4888 | I103: =I77 -> -2118.9982 | L103: Tesla's financial projections indicate improving profitability and cash flow generation between 2026 and 2030. Revenue is expected to increase from $99.26 billion to $141.27 billion, while operating income grows from $5.56 billion to $16.29 billion. Operating cash flow is projected to rise from $14.53 billion to $22.82 billion. However, significant capital expenditures limit free cash flow during the earlier forecast years, with unlevered free cash flow increasing from $1.69 billion in 2026 to $7.98 billion by 2030. Using a weighted average cost of capital (WACC) of 15.50% and a terminal growth rate of 3%, the discounted cash flow model estimates an enterprise value of $44.31 billion. Of this amount, $12.34 billion comes from forecasted cash flows, while $31.97 billion comes from terminal value. This means approximately 72% of the enterprise value depends on cash flows generated beyond 2030, making the valuation particularly sensitive to long-term growth and discount rate assumptions. After adjusting for cash, short-term investments, debt, and noncontrolling interests, Tesla's estimated equity value reaches $79.27 billion, equivalent to approximately $21.12 per share. Compared with the market price of $386.83, the model indicates an implied downside of approximately 94.54%. This significant difference suggests that the market may be pricing in future growth opportunities beyond those captured in the model, particularly autonomous driving, artificial intelligence, robotics, and energy storage. However, it could also reflect limitations in the forecasting assumptions. The model currently uses simplified projections for operating expenses, capital expenditures, working capital, and financing costs. Additionally, the WACC and capital structure assumptions require further validation. Overall, the analysis demonstrates that Tesla's projected financial performance improves considerably through 2030, but the current DCF assumptions produce a valuation substantially below the observed market price. Before reaching an investment conclusion, further sensitivity analysis, scenario testing, and validation of the underlying financial assumptions are necessary.
B104: other non cash adjustment | E104: =E78 -> 992.607 | F104: =F78 -> 1075.7471 | G104: =G78 -> 942.4536 | H104: =H78 -> 1035.6592 | I104: =I78 -> 706.33273
B105: capital expenditures | E105: =E80 -> 11911.284 | F105: =F80 -> 13984.712 | G105: =G80 -> 14136.804 | H105: =H80 -> 14240.314 | I105: =I80 -> 14126.655
B106: unlevered FCF | E106: =SUM(E100:E104)-E105 -> 1685.214 | F106: =SUM(F100:F104)-F105 -> 1657.5574 | G106: =SUM(G100:G104)-G105 -> 3472.556 | H106: =SUM(H100:H104)-H105 -> 6230.9125 | I106: =SUM(I100:I104)-I105 -> 7977.1932
B110: DCF valuation assumptions
D111: VALUE
B112: risk free rate | D112: 0.0512
B113: equity risk premium | D113: 0.055
B114: tesla beta | D114: 2
B115: cost of equity | D115: =D112+D114*D113 -> 0.1612
B116: pre tax cost of debt | D116: 0.05
B117: corporate tax rate | D117: 0.25
B118: equity weight | D118: 0.95
B119: debt weight | D119: 0.05
B120: after tax cost of debt | D120: =D116*(1-D117) -> 0.0375
B121: WACC | D121: =D115*D118+D120*D119 -> 0.155015
B122: terminal growth rate | D122: 0.03
B126: Discoutned cash flow valuation ($millions)
D127: 2025 actual | E127: 2026 forecast | F127: 2027 forecast | G127: 2028 forecast | H127: 2029 forecast | I127: 2030 forecast
B128: unlevered FCF | E128: =E106 -> 1685.214 | F128: =F106 -> 1657.5574 | G128: =G106 -> 3472.556 | H128: =H106 -> 6230.9125 | I128: =I106 -> 7977.1932
B129: Discount factor | E129: =1/(1+$D$121)^E131 -> 0.86578962 | F129: =1/(1+$D$121)^F131 -> 0.74959167 | G129: =1/(1+$D$121)^G131 -> 0.64898869 | H129: =1/(1+$D$121)^H131 -> 0.56188767 | I129: =1/(1+$D$121)^I131 -> 0.48647651
B130: present value of FCF | E130: =E128*E129 -> 1459.0408 | F130: =F128*F129 -> 1242.4912 | G130: =G128*G129 -> 2253.6496 | H130: =H128*H129 -> 3501.0729 | I130: =I128*I129 -> 3880.7171
B131: Forecast period | E131: 1 | F131: =E131+1 -> 2 | G131: =F131+1 -> 3 | H131: =G131+1 -> 4 | I131: =H131+1 -> 5
B135: terminal value
B136: 2030FCFF | C136: =I106 -> 7977.1932
B137: terminal growth rate | C137: =D122 -> 0.03
B138: WACC | C138: =D121 -> 0.155015
...

Sheet TSLA scenario analysis 
B2: Scenario Summary
D3: Current Values: | E3: bear case | F3: base case | G3: bull case
E4: Created by M Anderson on 10/21/2026 | F4: Created by M Anderson on 10/21/2026 | G4: Created by M Anderson on 10/21/2026
B5: Changing Cells:
C6: $C$201 | D6: 0 | E6: -0.05 | F6: 0 | G6: 0.05
C7: $C$202 | D7: 0 | E7: -0.02 | F7: 0 | G7: 0.02
C8: $C$203 | D8: 0 | E8: 0.15 | F8: 0 | G8: -0.15
B9: Result Cells:
C10: $C$157 | D10: 79265.244 | E10: 48257.181 | F10: 79265.244 | G10: 114976.94
C11: $C$159 | D11: 21.123699 | E11: 12.860241 | F11: 21.123699 | G11: 30.640645
B12: Notes: Current Values column represents values of changing cells at
B13: time Scenario Summary Report was created. Changing cells for each
B14: scenario are highlighted in gray.

Sheet Financial Risk Assesment 
B2: Risk identification Matrix
B3: risk category | C3: primary risk | D3: financial impact | E3: likelyhood (1-5) | F3: imapact (1-5) | G3: Risk score | H3: Risk Level | M3: Tesla's financial risk assessment identifies profitability (20/25) as its highest risk, followed by revenue, capital expenditures, and valuation (16/25 each). Stress testing demonstrated significant operating leverage, with a 10% increase in operating costs resulting in negative operating income. Moderate cash flow stress also produced approximately $1.48 billion in negative free cash flow. Meanwhile, liquidity (6/25) and solvency (4/25) present relatively lower risks, supported by strong liquidity ratios and limited financial leverage. Overall, Tesla's primary modeled financial risks stem from profitability pressures and investment requirements rather than immediate balance sheet concerns. Risk scores reflect qualitative judgments based on hypothetical scenarios.
B4: revenue | C4: slower vehicle demand | D4: lower sales growth | E4: 4 | F4: 4 | G4: =E4*F4 -> 16 | H4: =IF(G4>=15,"High",IF(G4>=8,"Moderate","Low")) -> High
B5: profitability | C5: price competition | D5: margin compression | E5: 4 | F5: 5 | G5: =E5*F5 -> 20 | H5: =IF(G5>=15,"High",IF(G5>=8,"Moderate","Low")) -> High
B6: liquidity | C6: higher cash requirement | D6: reduced cash reserves | E6: 2 | F6: 3 | G6: =E6*F6 -> 6 | H6: =IF(G6>=15,"High",IF(G6>=8,"Moderate","Low")) -> Low
B7: solvency | C7: debt and fixed obligation | D7: reduced financial flexibility | E7: 2 | F7: 2 | G7: =E7*F7 -> 4 | H7: =IF(G7>=15,"High",IF(G7>=8,"Moderate","Low")) -> Low
B8: capex | C8: higher investment spending | D8: lower free cash flo w | E8: 4 | F8: 4 | G8: =E8*F8 -> 16 | H8: =IF(G8>=15,"High",IF(G8>=8,"Moderate","Low")) -> High
B9: valuation | C9: changes in wacc and growth | D9: lower intrinsic valuation | E9: 4 | F9: 4 | G9: =E9*F9 -> 16 | H9: =IF(G9>=15,"High",IF(G9>=8,"Moderate","Low")) -> High
B12: liquidity and solvency analysis | F12: Tesla's liquidity position improved from 2024 to 2025, with its current ratio increasing from 2.03 to 2.16 and its quick ratio rising from 1.42 to 1.53. This suggests the company has strengthened its ability to cover short-term obligations. Additionally, debt-to-equity declined from 11.3% to 10.2%, indicating relatively low financial leverage and reduced balance sheet risk. However, the operating cash flow ratio decreased from 0.52 to 0.47, suggesting weaker operating cash generation relative to current liabilities. Despite this decline, Tesla's free cash flow margin improved from 3.7% to 6.6%, reflecting lower capital expenditures rather than stronger operating performance. Overall, Tesla demonstrates a relatively strong liquidity position and limited debt exposure, although declining operating cash flow coverage remains an important risk to monitor.
C13: 2025 | D13: 2024
B14: current ratio | C14: ='tesla financial modeling '!D66/'tesla financial modeling '!D70 -> 2.1644069 | D14: ='tesla financial modeling '!E66/'tesla financial modeling '!E70 -> 2.0249124
B15: quick ratio | C15: =('tesla financial modeling '!D61+'tesla financial modeling '!D62+'tesla financial modeling '!D63)/'tesla financial modeling '!D70 -> 1.5335499 | D15: =('tesla financial modeling '!E61+'tesla financial modeling '!E62+'tesla financial modeling '!E63)/'tesla financial modeling '!E70 -> 1.4219146
B16: cash ratio | C16: =('tesla financial modeling '!D61+'tesla financial modeling '!D62)/'tesla financial modeling '!D70 -> 1.3892603 | D16: =('tesla financial modeling '!E61+'tesla financial modeling '!E62)/'tesla financial modeling '!E70 -> 1.2686236
B17: debt to equity | C17: ='tesla financial modeling '!D72/'tesla financial modeling '!D76 -> 0.10197597 | D17: ='tesla financial modeling '!E72/'tesla financial modeling '!E76 -> 0.11264109
B18: debt to asset | C18: ='tesla financial modeling '!D72/'tesla financial modeling '!D69 -> 0.060781098 | D18: ='tesla financial modeling '!E72/'tesla financial modeling '!E69 -> 0.067281068
B19: operating cash flow ratio | C19: ='tesla financial modeling '!D81/'tesla financial modeling '!D70 -> 0.46499968 | D19: ='tesla financial modeling '!E81/'tesla financial modeling '!E70 -> 0.51778217
B20: free cash flow margin | C20: ='tesla financial modeling '!D83/'tesla financial modeling '!D44 -> 0.065593133 | D20: ='tesla financial modeling '!E83/'tesla financial modeling '!E44 -> 0.036656771
B24: Revenue stress testing ($millions)
C25: base | D25: mild | E25: moderate | F25: severe | H25: Tesla's revenue stress test demonstrates significant sensitivity to declining sales. Under the assumed cost structure of 80% variable costs and 20% fixed costs, a 10% decline in projected 2026 revenue reduces operating income from $5.56 billion to $3.13 billion, representing a decline of approximately 44%. Under moderate stress, operating income falls to approximately $696 million, reducing operating margins from 5.60% to 0.88%. In the severe scenario, a 30% revenue decline results in an operating loss of approximately $1.73 billion. These findings suggest that Tesla's profitability is highly sensitive to revenue performance, particularly when fixed operating expenses remain unchanged. Although the results depend on hypothetical cost assumptions, they highlight the importance of revenue stability and cost flexibility in managing financial risk.
B26: revenue shock | C26: 0 | D26: -0.1 | E26: -0.2 | F26: -0.3
B27: 2026 revenue | C27: ='TSLA forecastin & evaluation '!E28 -> 99260.7 | D27: =$C$27*(1+D26) -> 89334.63 | E27: =$C$27*(1+E26) -> 79408.56 | F27: =$C$27*(1+F26) -> 69482.49
B28: operating income | C28: ='TSLA forecastin & evaluation '!E52 -> 5555.642 | D28: =D27-(($C$27-$C$28)*80%*(1+D26))-($C$27-$C$28)*20% -> 3125.9766 | E28: =E27-(($C$27-$C$28)*80%*(1+E26))-($C$27-$C$28)*20% -> 696.31128 | F28: =F27-(($C$27-$C$28)*80%*(1+F26))-($C$27-$C$28)*20% -> -1733.3541
B29: operating margin | C29: =C28/C27 -> 0.055970208 | D29: =D28/D27 -> 0.034991768 | E29: =E28/E27 -> 0.0087687181 | F29: =F28/F27 -> -0.024946632
B30: revenue change | C30: =C27-$C$27 -> 0 | D30: =D27-$C$27 -> -9926.07 | E30: =E27-$C$27 -> -19852.14 | F30: =F27-$C$27 -> -29778.21
B31: operating income change | C31: =C28-$C$28 -> 0 | D31: =D28-$C$28 -> -2429.6654 | E31: =E28-$C$28 -> -4859.3307 | F31: =F28-$C$28 -> -7288.9961
B38: margin & cost stress testing
C39: base | D39: mild | E39: moderate | F39: severe
B40: operating cost shock | C40: 0 | D40: 0.05 | E40: 0.1 | F40: 0.15 | H40: Tesla's margin and cost stress test highlights significant exposure to rising operating expenses. Holding projected 2026 revenue constant at $99.26 billion, a 5% increase in operating costs reduces operating income from $5.56 billion to approximately $870 million, representing an 84% decline. Under moderate stress, a 10% increase in operating costs results in an operating loss of approximately $3.81 billion. In the severe scenario, operating losses reach $8.50 billion, with operating margins falling to -8.56%. These findings demonstrate that Tesla's projected profitability is highly sensitive to cost inflation. While the scenarios are hypothetical, they emphasize the importance of controlling production expenses, maintaining pricing power, and improving operational efficiency.
B41: 2026 revenue | C41: =$C$27 -> 99260.7 | D41: =$C$27 -> 99260.7 | E41: =$C$27 -> 99260.7 | F41: =$C$27 -> 99260.7
B42: base operation cost | C42: =$C$27-$C$28 -> 93705.058 | D42: =$C$27-$C$28 -> 93705.058 | E42: =$C$27-$C$28 -> 93705.058 | F42: =$C$27-$C$28 -> 93705.058
B43: stressed operation cost | C43: =C42*(1+C40) -> 93705.058 | D43: =D42*(1+D40) -> 98390.311 | E43: =E42*(1+E40) -> 103075.56 | F43: =F42*(1+F40) -> 107760.82
B44: operating income | C44: =C41-C43 -> 5555.642 | D44: =D41-D43 -> 870.3891 | E44: =E41-E43 -> -3814.8638 | F44: =F41-F43 -> -8500.1167
B45: operating margin | C45: =C44/C41 -> 0.055970208 | D45: =D44/D41 -> 0.0087687181 | E45: =E44/E41 -> -0.038432771 | F45: =F44/F41 -> -0.085634261
B46: operating income change | C46: =C44-$C$28 -> 0 | D46: =D44-$C$28 -> -4685.2529 | E46: =E44-$C$28 -> -9370.5058 | F46: =F44-$C$28 -> -14055.759
B52: CF stress testing ($millions)
C53: base | D53: mild | E53: moderate | F53: severe | H53: Tesla's cash flow stress test highlights its sensitivity to declining operating cash flow and increasing capital expenditures. Under the mild scenario, projected 2026 free cash flow declines from $2.62 billion to approximately $574 million, representing a 78% reduction. Under moderate stress, free cash flow turns negative at approximately $1.48 billion, while the severe scenario produces negative free cash flow of $3.52 billion. These results suggest that Tesla's projected cash generation may be insufficient to support its planned capital expenditures during periods of financial pressure. Although Tesla maintains substantial liquidity reserves, sustained negative free cash flow could reduce financial flexibility and increase reliance on existing cash or external financing. These scenarios are hypothetical and demonstrate the importance of monitoring operating cash generation alongside future investment requirements.
B54: operating cost shock | C54: 0 | D54: -0.1 | E54: -0.2 | F54: -0.3
B55: capex increase | C55: 0 | D55: 0.05 | E55: 0.1 | F55: 0.15
B56: operating cash flow | C56: ='TSLA forecastin & evaluation '!E79 -> 14533.998 | D56: =$C$56*(1+D54) -> 13080.598 | E56: =$C$56*(1+E54) -> 11627.198 | F56: =$C$56*(1+F54) -> 10173.799
B57: capex | C57: ='TSLA forecastin & evaluation '!E80 -> 11911.284 | D57: =$C$57*(1+D55) -> 12506.848 | E57: =$C$57*(1+E55) -> 13102.412 | F57: =$C$57*(1+F55) -> 13697.977
B58: free cash flow | C58: ='TSLA forecastin & evaluation '!E81 -> 2622.714 | D58: =D56-D57 -> 573.75 | E58: =E56-E57 -> -1475.214 | F58: =F56-F57 -> -3524.178
B59: FCF margin | C59: =C58/$C$27 -> 0.026422481 | D59: =D58/$C$27 -> 0.0057802333 | E59: =E58/$C$27 -> -0.014862015 | F59: =F58/$C$27 -> -0.035504263
B60: FCF change vs. Base % | C60: =(C58-$C$58)/$C$58 -> 0 | D60: =(D58-$C$58)/$C$58 -> -0.78123806 | E60: =(E58-$C$58)/$C$58 -> -1.5624761 | F60: =(F58-$C$58)/$C$58 -> -2.3437142
B61: FCF status | C61: =IF(C58<0,"Negative FCF","Positive FCF") -> Positive FCF | D61: =IF(D58<0,"Negative FCF","Positive FCF") -> Positive FCF | E61: =IF(E58<0,"Negative FCF","Positive FCF") -> Negative FCF | F61: =IF(F58<0,"Negative FCF","Positive FCF") -> Negative FCF
B68: Montecarlos simulation
B69: Assumption | G69: Monte Carlos Results | J69: Tesla's Monte Carlo simulation evaluates 1,000 potential free cash flow outcomes for 2026, incorporating hypothetical 10% volatility in operating cash flow and capital expenditures. The simulation produces an average free cash flow of approximately $2.64 billion, closely aligned with the base forecast of $2.62 billion. Approximately 7.3% of simulated outcomes result in negative free cash flow, highlighting potential downside exposure when operating cash generation weakens or capital expenditures increase. The 5th percentile outcome of approximately negative $478 million indicates that adverse combinations of these factors could push Tesla into a cash flow deficit. Although the simulation suggests positive free cash flow across most modeled outcomes, the results depend heavily on the selected volatility assumptions and distribution of potential financial outcomes. Consequently, these findings should be interpreted as an illustrative assessment of financial risk rather than a precise prediction.
B70: base operation cash flow | C70: =$C$56 -> 14533.998 | G70: Avg FCF | H70: =AVERAGE(E76:E1075) -> 2695.9798
B71: base capex | C71: =$C$57 -> 11911.284 | G71: Minimum FCF | H71: =MIN(E76:E1075) -> -3671.9268
B72: OCF volatility | C72: 0.1 | G72: Maximum FCF | H72: =MAX(E76:E1075) -> 8425.2843
B73: CAPEX Volatility | C73: 0.1 | G73: Probability of Negative FCF | H73: =COUNTIF(E76:E1075,"<0")/COUNT(E76:E1075) -> 0.075
B74: Number of simulations | C74: 1000 | G74: 5th Percentile FCF | H74: =_xlfn.PERCENTILE.INC(E76:E1075,0.05) -> -446.1827
B75: simulation | C75: Simulated OCF | D75: Simulated Capex | E75: Simulated FCF | G75: 95th Percentile FCF | H75: =_xlfn.PERCENTILE.INC(E76:E1075,0.95) -> 5631.38
B76: 1 | C76: =$C$70*(1+_xlfn.NORM.S.INV(RAND())*$C$72) -> 14333.332 | D76: =$C$71*(1+_xlfn.NORM.S.INV(RAND())*$C$73) -> 11196.729 | E76: =C76-D76 -> 3136.6032
B77: =B76+1 -> 2 | C77: =$C$70*(1+_xlfn.NORM.S.INV(RAND())*$C$72) -> 15539.17 | D77: =$C$71*(1+_xlfn.NORM.S.INV(RAND())*$C$73) -> 11970.431 | E77: =C77-D77 -> 3568.7384
B78: =B77+1 -> 3 | C78: =$C$70*(1+_xlfn.NORM.S.INV(RAND())*$C$72) -> 17356.294 | D78: =$C$71*(1+_xlfn.NORM.S.INV(RAND())*$C$73) -> 10663.848 | E78: =C78-D78 -> 6692.4462
B79: =B78+1 -> 4 | C79: =$C$70*(1+_xlfn.NORM.S.INV(RAND())*$C$72) -> 14174.358 | D79: =$C$71*(1+_xlfn.NORM.S.INV(RAND())*$C$73) -> 12098.298 | E79: =C79-D79 -> 2076.0596
B80: =B79+1 -> 5 | C80: =$C$70*(1+_xlfn.NORM.S.INV(RAND())*$C$72) -> 15647.99 | D80: =$C$71*(1+_xlfn.NORM.S.INV(RAND())*$C$73) -> 11979.005 | E80: =C80-D80 -> 3668.9859
B81: =B80+1 -> 6 | C81: =$C$70*(1+_xlfn.NORM.S.INV(RAND())*$C$72) -> 14257.309 | D81: =$C$71*(1+_xlfn.NORM.S.INV(RAND())*$C$73) -> 12476.962 | E81: =C81-D81 -> 1780.3472
B82: =B81+1 -> 7 | C82: =$C$70*(1+_xlfn.NORM.S.INV(RAND())*$C$72) -> 16937.049 | D82: =$C$71*(1+_xlfn.NORM.S.INV(RAND())*$C$73) -> 12938.218 | E82: =C82-D82 -> 3998.8309
B83: =B82+1 -> 8 | C83: =$C$70*(1+_xlfn.NORM.S.INV(RAND())*$C$72) -> 14665.84 | D83: =$C$71*(1+_xlfn.NORM.S.INV(RAND())*$C$73) -> 12667.687 | E83: =C83-D83 -> 1998.1534
B84: =B83+1 -> 9 | C84: =$C$70*(1+_xlfn.NORM.S.INV(RAND())*$C$72) -> 15544.161 | D84: =$C$71*(1+_xlfn.NORM.S.INV(RAND())*$C$73) -> 10970.21 | E84: =C84-D84 -> 4573.9511
B85: =B84+1 -> 10 | C85: =$C$70*(1+_xlfn.NORM.S.INV(RAND())*$C$72) -> 15389.329 | D85: =$C$71*(1+_xlfn.NORM.S.INV(RAND())*$C$73) -> 12373.679 | E85: =C85-D85 -> 3015.6493
B86: =B85+1 -> 11 | C86: =$C$70*(1+_xlfn.NORM.S.INV(RAND())*$C$72) -> 16788.191 | D86: =$C$71*(1+_xlfn.NORM.S.INV(RAND())*$C$73) -> 10498.144 | E86: =C86-D86 -> 6290.0465
B87: =B86+1 -> 12 | C87: =$C$70*(1+_xlfn.NORM.S.INV(RAND())*$C$72) -> 17004.473 | D87: =$C$71*(1+_xlfn.NORM.S.INV(RAND())*$C$73) -> 10768.162 | E87: =C87-D87 -> 6236.3115
B88: =B87+1 -> 13 | C88: =$C$70*(1+_xlfn.NORM.S.INV(RAND())*$C$72) -> 13808.568 | D88: =$C$71*(1+_xlfn.NORM.S.INV(RAND())*$C$73) -> 12890.749 | E88: =C88-D88 -> 917.81871
... B1075: =B1074+1 -> 1000 | C1075: =$C$70*(1+_xlfn.NORM.S.INV(RAND())*$C$72) -> 14586.183 | D1075: =$C$71*(1+_xlfn.NORM.S.INV(RAND())*$C$73) -> 10984.848 | E1075: =C1075-D1075 -> 3601.335
